cooper/__init__.py
cooper/cmp.py
cooper/py.typed
cooper/constraints/__init__.py
cooper/constraints/constraint.py
cooper/constraints/constraint_state.py
cooper/formulations/__init__.py
cooper/formulations/formulations.py
cooper/formulations/utils.py
cooper/multipliers/__init__.py
cooper/multipliers/multipliers.py
cooper/optim/__init__.py
cooper/optim/optimizer.py
cooper/optim/unconstrained_optimizer.py
cooper/optim/constrained_optimizers/__init__.py
cooper/optim/constrained_optimizers/alternating_optimizer.py
cooper/optim/constrained_optimizers/constrained_optimizer.py
cooper/optim/constrained_optimizers/extrapolation_optimizer.py
cooper/optim/constrained_optimizers/simultaneous_optimizer.py
cooper/optim/torch_optimizers/__init__.py
cooper/optim/torch_optimizers/extragradient.py
cooper/optim/torch_optimizers/nupi_optimizer.py
cooper/penalty_coefficients/__init__.py
cooper/penalty_coefficients/penalty_coefficient_updaters.py
cooper/penalty_coefficients/penalty_coefficients.py
cooper/utils/__init__.py
cooper/utils/annotations.py
cooper/utils/utils.py
cooper_optim-1.0.1.dist-info/METADATA
cooper_optim-1.0.1.dist-info/WHEEL
cooper_optim-1.0.1.dist-info/licenses/LICENSE
cooper_optim-1.0.1.dist-info/RECORD
