Metadata-Version: 2.4
Name: cooper-optim
Version: 1.0.1
Summary: A library for Lagrangian-based constrained optimization in PyTorch
Project-URL: Homepage, https://github.com/cooper-org/cooper
Project-URL: Download, https://pypi.org/project/cooper-optim/#files
Project-URL: Documentation, https://cooper.readthedocs.io
Project-URL: Source, https://github.com/cooper-org/cooper
Project-URL: Tracker, https://github.com/cooper-org/cooper/issues
Author-email: Jose Gallego-Posada <jgalle29@gmail.com>, Juan Ramirez <juan43.ramirez@gmail.com>, Meraj Hashemizadeh <merajhashemi@yahoo.co.uk>
Maintainer-email: Jose Gallego-Posada <jgalle29@gmail.com>, Juan Ramirez <juan43.ramirez@gmail.com>, Meraj Hashemizadeh <merajhashemi@yahoo.co.uk>
License-Expression: MIT
License-File: LICENSE
Keywords: lagrangian optimization,machine learning,non-convex constrained optimization,pytorch
Classifier: Development Status :: 5 - Production/Stable
Classifier: Intended Audience :: Developers
Classifier: Intended Audience :: Education
Classifier: Intended Audience :: Science/Research
Classifier: Natural Language :: English
Classifier: Operating System :: OS Independent
Classifier: Programming Language :: Python
Classifier: Programming Language :: Python :: 3 :: Only
Classifier: Programming Language :: Python :: 3.9
Classifier: Programming Language :: Python :: 3.10
Classifier: Programming Language :: Python :: 3.11
Classifier: Programming Language :: Python :: 3.12
Classifier: Programming Language :: Python :: 3.13
Classifier: Programming Language :: Python :: Implementation :: CPython
Classifier: Topic :: Scientific/Engineering
Classifier: Topic :: Scientific/Engineering :: Artificial Intelligence
Classifier: Topic :: Scientific/Engineering :: Mathematics
Classifier: Topic :: Software Development
Classifier: Topic :: Software Development :: Libraries
Classifier: Topic :: Software Development :: Libraries :: Python Modules
Classifier: Typing :: Typed
Requires-Python: >=3.9
Requires-Dist: torch>=1.13.1
Requires-Dist: typing-extensions>=4.13.0
